{
    "684488b1c9ead5b831d49ac8": {
        "$type": "RealismMod.WeaponMod, RealismMod",
        "ItemID": "684488b1c9ead5b831d49ac8",
        "Name": "M16A2 5.56x45 upper reciever",
        "ModType": "",
        "ModMalfunctionChance": 2,
        "Accuracy": 1,
        "HeatFactor": 1.0,
        "CoolFactor": 1.03,
        "DurabilityBurnModificator": 0.94,
        "ConflictingItems": [],
        "Ergonomics": 5,
        "Weight": 0.246,
        "VerticalRecoil": 0,
        "HorizontalRecoil": 0,
        "ChamberSpeed": 0,
        "LoyaltyLevel": 4,
        "AutoROF": 1,
        "SemiROF": 2,
        "Convergence": 2
    },
    "684489fe2cc79fb0b0fd98af": {
        "$type": "RealismMod.WeaponMod, RealismMod",
        "ItemID": "684489fe2cc79fb0b0fd98af",
        "Name": "M16A1 5.56x45 upper reciever",
        "ModType": "",
        "ModMalfunctionChance": -1,
        "Accuracy": 2,
        "HeatFactor": 0.97,
        "CoolFactor": 1.01,
        "DurabilityBurnModificator": 0.94,
        "ConflictingItems": [],
        "Ergonomics": 1,
        "Weight": 0.246,
        "VerticalRecoil": 0,
        "HorizontalRecoil": 0,
        "ChamberSpeed": 0,
        "LoyaltyLevel": 4,
        "AutoROF": 1,
        "SemiROF": 1,
        "Convergence": 7
    },
    "6838e20d9d86f2aa3a05fc37": {
        "$type": "RealismMod.WeaponMod, RealismMod",
        "ItemID": "6838e20d9d86f2aa3a05fc37",
        "Name": "Echoes Defense M45A1 custom pistol slide with ACRO mount",
        "ModType": "",
        "ModMalfunctionChance": 2,
        "Accuracy": 4,
        "HeatFactor": 1.03,
        "CoolFactor": 1.02,
        "DurabilityBurnModificator": 1,
        "ConflictingItems": [],
        "Ergonomics": 2,
        "Weight": 0.47,
        "VerticalRecoil": 0,
        "HorizontalRecoil": 0,
        "ChamberSpeed": 30,
        "LoyaltyLevel": 2,
        "AutoROF": 1,
        "SemiROF": 2,
        "Convergence": 2
    },
    "6837aa4c2491fc57390a6cc4": {
        "$type": "RealismMod.WeaponMod, RealismMod",
        "ItemID": "6837aa4c2491fc57390a6cc4",
        "Name": "M1911A1 pistol slide with RMR mount",
        "ModType": "",
        "ModMalfunctionChance": 1,
        "Accuracy": -2,
        "HeatFactor": 0.98,
        "CoolFactor": 1.04,
        "DurabilityBurnModificator": 1,
        "ConflictingItems": [],
        "Ergonomics": 4,
        "Weight": 0.38,
        "VerticalRecoil": 0,
        "HorizontalRecoil": 0,
        "ChamberSpeed": 14,
        "LoyaltyLevel": 1,
        "AutoROF": 0,
        "SemiROF": 3,
        "Convergence": 0
    }
}