{
    "deee28079e76d537f532021c": {
        "$type": "RealismMod.Gun, RealismMod",
        "ItemID": "deee28079e76d537f532021c",
        "Name": "Surgeon Rifles 1581 XL action .338 LM bolt-action sniper rifle",
        "WeapType": "",
        "OperationType": "manual",
        "WeapAccuracy": 0,
        "BaseTorque": 2,
        "HasShoulderContact": false,
        "Ergonomics": 72,
        "VerticalRecoil": 370,
        "HorizontalRecoil": 297,
        "Dispersion": 2,
        "CameraRecoil": 0.15,
        "VisualMulti": 2,
        "Convergence": 1,
        "RecoilAngle": 90,
        "BaseMalfunctionChance": 0.1877,
        "HeatFactorGun": 1,
        "HeatFactorByShot": 6.72,
        "CoolFactorGun": 0.1,
        "CoolFactorGunMods": 1,
        "AllowOverheat": true,
        "CenterOfImpact": 0.005,
        "HipAccuracyRestorationDelay": 0.2,
        "HipAccuracyRestorationSpeed": 7,
        "HipInnaccuracyGain": 0.16,
        "ShotgunDispersion": 0,
        "Velocity": 14.57,
        "RecoilDamping": 0.8,
        "RecoilHandDamping": 0.41,
        "WeaponAllowADS": false,
        "Weight": 1.235,
        "DurabilityBurnRatio": 1.05,
        "AutoROF": 30,
        "SemiROF": 450,
        "LoyaltyLevel": 4,
        "BaseReloadSpeedMulti": 1,
        "BaseChamberSpeedMulti": 1.95,
        "MinChamberSpeed": 0.7,
        "MaxChamberSpeed": 1.25,
        "IsManuallyOperated": true,
        "BaseChamberCheckSpeed": 3,
        "BaseFixSpeed": 3,
        "OffsetRotation": 0.01,
        "RecoilIntensity": 0.16,
        "RecoilCenter": {
            "x": 0,
            "y": -0.4,
            "z": 0
        }
    },
    "f1b1a0db4986e718711a8e80": {
        "$type": "RealismMod.WeaponMod, RealismMod",
        "ItemID": "f1b1a0db4986e718711a8e80",
        "Name": "MDT AICS style 3.715 inch 5-round magazine",
        "ModType": "",
        "ReloadSpeed": 3,
        "Ergonomics": 1,
        "MalfunctionChance": -2,
        "LoadUnloadModifier": 5,
        "CheckTimeModifier": -1,
        "ConflictingItems": [],
        "Weight": 0.5,
        "VerticalRecoil": 0,
        "HorizontalRecoil": 0,
        "LoyaltyLevel": 2
    },
    "05d4400c84ab3eb0e7722625": {
        "$type": "RealismMod.WeaponMod, RealismMod",
        "ItemID": "05d4400c84ab3eb0e7722625",
        "Name": "MDT AICS style 3.715 inch 10-round magazine",
        "ModType": "",
        "ReloadSpeed": 6,
        "Ergonomics": 3,
        "MalfunctionChance": 0,
        "LoadUnloadModifier": 6,
        "CheckTimeModifier": 0,
        "ConflictingItems": [],
        "Weight": 0.5,
        "VerticalRecoil": 0,
        "HorizontalRecoil": 0,
        "LoyaltyLevel": 2
    },
    "4efd57bf8ef993ea989884cd": {
        "$type": "RealismMod.WeaponMod, RealismMod",
        "ItemID": "4efd57bf8ef993ea989884cd",
        "Name": "MDT ESS 12 inch forend",
        "ModType": "",
        "VerticalRecoil": -6,
        "HorizontalRecoil": -4,
        "Dispersion": -3,
        "AimSpeed": 2,
        "Ergonomics": 4,
        "Accuracy": 15,
        "HeatFactor": 1.03,
        "CoolFactor": 0.95,
        "ConflictingItems": [
            "5bfebc530db834001d23eb65"
        ],
        "Weight": 0.6,
        "LoyaltyLevel": 3,
        "AimStability": 9
    },
    "8bf881390b6747006aae77a3": {
        "$type": "RealismMod.WeaponMod, RealismMod",
        "ItemID": "8bf881390b6747006aae77a3",
        "Name": "MDT ESS 15 inch forend",
        "ModType": "",
        "VerticalRecoil": -5,
        "HorizontalRecoil": -2,
        "Dispersion": -3,
        "AimSpeed": 2,
        "Ergonomics": 6,
        "Accuracy": 15,
        "HeatFactor": 0.98,
        "CoolFactor": 0.97,
        "ConflictingItems": [
            "c68564cf5a0d02bc54ea5725",
            "5bf36d856d9d529d60cfabb4"
        ],
        "Weight": 0.8,
        "LoyaltyLevel": 3,
        "AimStability": 7
    },
    "ff31402cb7b0b1d43491337c": {
        "$type": "RealismMod.WeaponMod, RealismMod",
        "ItemID": "ff31402cb7b0b1d43491337c",
        "Name": "MDT ESS 18 inch forend",
        "ModType": "",
        "VerticalRecoil": -4,
        "HorizontalRecoil": -3,
        "Dispersion": -3,
        "AimSpeed": 0,
        "Ergonomics": 4,
        "Accuracy": 15,
        "HeatFactor": 0.97,
        "CoolFactor": 0.99,
        "ConflictingItems": [
            "c68564cf5a0d02bc54ea5725",
            "5bf36d856d9d529d60cfabb4",
            "924d08fd140d56bc7e395091",
            "67e8c043679ab98cf5a9a894"
        ],
        "Weight": 1,
        "LoyaltyLevel": 3,
        "AimStability": 6
    },
    "277727478d7eb1da0e5b3354": {
        "$type": "RealismMod.WeaponMod, RealismMod",
        "ItemID": "277727478d7eb1da0e5b3354",
        "Name": "PGW Defense Timberwolf .338 LM 26 inch barrel",
        "ModType": "",
        "VerticalRecoil": -4,
        "HorizontalRecoil": 0,
        "AutoROF": 0,
        "SemiROF": 0,
        "ModMalfunctionChance": 0,
        "Convergence": 5,
        "Accuracy": 0,
        "CenterOfImpact": 0.03,
        "HeatFactor": 1.02,
        "CoolFactor": 1.04,
        "DurabilityBurnModificator": 1,
        "Velocity": 0.28,
        "ConflictingItems": [
            "5a6086ea4f39f99cd479502f",
            "5a608bf24f39f98ffc77720e",
            "58dd3ad986f77403051cba8f",
            "5e023e53d4353e3302577c4c",
            "5efb0c1bd79ff02a1f5e68d9",
            "5e023e6e34d52a55c3304f71",
            "5e023e88277cce2b522ff2b1"
        ],
        "Ergonomics": -20.5,
        "Weight": 1.93,
        "ShotgunDispersion": 1,
        "Loudness": 0,
        "LoyaltyLevel": 3
    },
    "549343528ae0e70c0d7d2786": {
        "$type": "RealismMod.WeaponMod, RealismMod",
        "ItemID": "549343528ae0e70c0d7d2786",
        "Name": "X-Caliber 416R Stainless Fluted .338 LM 28 inch barrel",
        "ModType": "",
        "VerticalRecoil": 0,
        "HorizontalRecoil": 0,
        "AutoROF": 0,
        "SemiROF": 0,
        "ModMalfunctionChance": 0,
        "Convergence": 4,
        "Accuracy": 4,
        "CenterOfImpact": 0.02,
        "HeatFactor": 1.04,
        "CoolFactor": 1.04,
        "DurabilityBurnModificator": 1,
        "Velocity": -0.07,
        "ConflictingItems": [
            "5a6086ea4f39f99cd479502f",
            "5a608bf24f39f98ffc77720e",
            "58dd3ad986f77403051cba8f",
            "5e023e53d4353e3302577c4c",
            "5efb0c1bd79ff02a1f5e68d9",
            "5e023e6e34d52a55c3304f71",
            "5e023e88277cce2b522ff2b1"
        ],
        "Ergonomics": -21.5,
        "Weight": 1.93,
        "ShotgunDispersion": 1,
        "Loudness": 0,
        "LoyaltyLevel": 3
    },
    "f8c59c78b4d984a2ce1d298d": {
        "$type": "RealismMod.WeaponMod, RealismMod",
        "ItemID": "f8c59c78b4d984a2ce1d298d",
        "Name": "X-Caliber 416R Stainless Fluted .338 LM 26 inch barrel",
        "ModType": "",
        "VerticalRecoil": -4,
        "HorizontalRecoil": 0,
        "AutoROF": 0,
        "SemiROF": 0,
        "ModMalfunctionChance": 0,
        "Convergence": 1,
        "Accuracy": 1,
        "CenterOfImpact": 0.03,
        "HeatFactor": 0.98,
        "CoolFactor": 0.97,
        "DurabilityBurnModificator": 1,
        "Velocity": 1.92,
        "ConflictingItems": [
            "5a6086ea4f39f99cd479502f",
            "5a608bf24f39f98ffc77720e",
            "58dd3ad986f77403051cba8f",
            "5e023e53d4353e3302577c4c",
            "5efb0c1bd79ff02a1f5e68d9",
            "5e023e6e34d52a55c3304f71",
            "5e023e88277cce2b522ff2b1"
        ],
        "Ergonomics": -20.5,
        "Weight": 1.78,
        "ShotgunDispersion": 1,
        "Loudness": 0,
        "LoyaltyLevel": 3
    },
    "aab94c09a091574e55810eba": {
        "$type": "RealismMod.WeaponMod, RealismMod",
        "ItemID": "aab94c09a091574e55810eba",
        "Name": "X-Caliber 416R Stainless Fluted .338 LM 24 inch barrel",
        "ModType": "",
        "VerticalRecoil": -3,
        "HorizontalRecoil": 0,
        "AutoROF": 0,
        "SemiROF": 0,
        "ModMalfunctionChance": 0,
        "Convergence": 7,
        "Accuracy": 1,
        "CenterOfImpact": 0.02,
        "HeatFactor": 0.99,
        "CoolFactor": 0.97,
        "DurabilityBurnModificator": 1,
        "Velocity": 1.13,
        "ConflictingItems": [
            "5a6086ea4f39f99cd479502f",
            "5a608bf24f39f98ffc77720e",
            "58dd3ad986f77403051cba8f",
            "5e023e53d4353e3302577c4c",
            "5efb0c1bd79ff02a1f5e68d9",
            "5e023e6e34d52a55c3304f71",
            "5e023e88277cce2b522ff2b1"
        ],
        "Ergonomics": -19.5,
        "Weight": 1.489,
        "ShotgunDispersion": 1,
        "Loudness": 0,
        "LoyaltyLevel": 3
    },
    "c2fb28cafc78fbd58e9ada1d": {
        "$type": "RealismMod.WeaponMod, RealismMod",
        "ItemID": "c2fb28cafc78fbd58e9ada1d",
        "Name": "X-Caliber 416R Stainless Fluted .338 LM 22 inch barrel",
        "ModType": "",
        "VerticalRecoil": -2,
        "HorizontalRecoil": 0,
        "AutoROF": 0,
        "SemiROF": 0,
        "ModMalfunctionChance": 0,
        "Convergence": 4,
        "Accuracy": 1,
        "CenterOfImpact": 0.04,
        "HeatFactor": 1.03,
        "CoolFactor": 0.97,
        "DurabilityBurnModificator": 1,
        "Velocity": 1.37,
        "ConflictingItems": [
            "5a6086ea4f39f99cd479502f",
            "5a608bf24f39f98ffc77720e",
            "58dd3ad986f77403051cba8f",
            "5e023e53d4353e3302577c4c",
            "5efb0c1bd79ff02a1f5e68d9",
            "5e023e6e34d52a55c3304f71",
            "5e023e88277cce2b522ff2b1"
        ],
        "Ergonomics": -18.5,
        "Weight": 1.343,
        "ShotgunDispersion": 1,
        "Loudness": 0,
        "LoyaltyLevel": 3
    },
    "edf82ccea7041e055852e7dc": {
        "$type": "RealismMod.WeaponMod, RealismMod",
        "ItemID": "edf82ccea7041e055852e7dc",
        "Name": "X-Caliber 416R Stainless Fluted .338 LM 20 inch barrel",
        "ModType": "",
        "VerticalRecoil": -1,
        "HorizontalRecoil": 0,
        "AutoROF": 0,
        "SemiROF": 0,
        "ModMalfunctionChance": 0,
        "Convergence": 4,
        "Accuracy": 0,
        "CenterOfImpact": 0.02,
        "HeatFactor": 1.03,
        "CoolFactor": 0.98,
        "DurabilityBurnModificator": 1,
        "Velocity": 1.09,
        "ConflictingItems": [
            "5a6086ea4f39f99cd479502f",
            "5a608bf24f39f98ffc77720e",
            "58dd3ad986f77403051cba8f",
            "5e023e53d4353e3302577c4c",
            "5efb0c1bd79ff02a1f5e68d9",
            "5e023e6e34d52a55c3304f71",
            "5e023e88277cce2b522ff2b1"
        ],
        "Ergonomics": -17.5,
        "Weight": 1.196,
        "ShotgunDispersion": 1,
        "Loudness": 0,
        "LoyaltyLevel": 3
    },
    "0ecb517dd3c38760877469df": {
        "$type": "RealismMod.WeaponMod, RealismMod",
        "ItemID": "0ecb517dd3c38760877469df",
        "Name": "X-Caliber 416R Stainless Fluted .338 LM 18 inch barrel",
        "ModType": "",
        "VerticalRecoil": 0,
        "HorizontalRecoil": 0,
        "AutoROF": 0,
        "SemiROF": 0,
        "ModMalfunctionChance": 0,
        "Convergence": 5,
        "Accuracy": -1,
        "CenterOfImpact": 0.03,
        "HeatFactor": 1.0,
        "CoolFactor": 0.96,
        "DurabilityBurnModificator": 1,
        "Velocity": 1.55,
        "ConflictingItems": [
            "5a6086ea4f39f99cd479502f",
            "5a608bf24f39f98ffc77720e",
            "58dd3ad986f77403051cba8f",
            "5e023e53d4353e3302577c4c",
            "5efb0c1bd79ff02a1f5e68d9",
            "5e023e6e34d52a55c3304f71",
            "5e023e88277cce2b522ff2b1"
        ],
        "Ergonomics": -16.5,
        "Weight": 1.049,
        "ShotgunDispersion": 1,
        "Loudness": 5,
        "LoyaltyLevel": 3
    },
    "67e8c043679ab98cf5a9a894": {
        "$type": "RealismMod.WeaponMod, RealismMod",
        "ItemID": "67e8c043679ab98cf5a9a894",
        "Name": "X-Caliber 416R Stainless Fluted .338 LM 16 inch barrel",
        "ModType": "",
        "VerticalRecoil": 1,
        "HorizontalRecoil": 0,
        "AutoROF": 0,
        "SemiROF": 0,
        "ModMalfunctionChance": 0,
        "Convergence": 8,
        "Accuracy": 5,
        "CenterOfImpact": 0.04,
        "HeatFactor": 1.03,
        "CoolFactor": 0.96,
        "DurabilityBurnModificator": 1,
        "Velocity": 0.09,
        "ConflictingItems": [
            "5a6086ea4f39f99cd479502f",
            "5a608bf24f39f98ffc77720e",
            "58dd3ad986f77403051cba8f",
            "5e023e53d4353e3302577c4c",
            "5efb0c1bd79ff02a1f5e68d9",
            "5e023e6e34d52a55c3304f71",
            "5e023e88277cce2b522ff2b1"
        ],
        "Ergonomics": -15.5,
        "Weight": 0.903,
        "ShotgunDispersion": 1,
        "Loudness": 10,
        "LoyaltyLevel": 3
    },
    "5bf36d856d9d529d60cfabb4": {
        "$type": "RealismMod.WeaponMod, RealismMod",
        "ItemID": "5bf36d856d9d529d60cfabb4",
        "Name": "X-Caliber 416R Stainless Fluted .338 LM 14 inch barrel",
        "ModType": "",
        "VerticalRecoil": 2,
        "HorizontalRecoil": 0,
        "AutoROF": 0,
        "SemiROF": 0,
        "ModMalfunctionChance": 0,
        "Convergence": 7,
        "Accuracy": 2,
        "CenterOfImpact": 0.03,
        "HeatFactor": 1.01,
        "CoolFactor": 0.98,
        "DurabilityBurnModificator": 1,
        "Velocity": -1.31,
        "ConflictingItems": [
            "5a6086ea4f39f99cd479502f",
            "5a608bf24f39f98ffc77720e",
            "58dd3ad986f77403051cba8f",
            "5e023e53d4353e3302577c4c",
            "5efb0c1bd79ff02a1f5e68d9",
            "5e023e6e34d52a55c3304f71",
            "5e023e88277cce2b522ff2b1"
        ],
        "Ergonomics": -14.5,
        "Weight": 0.756,
        "ShotgunDispersion": 1,
        "Loudness": 15,
        "LoyaltyLevel": 3
    },
    "203c45db79fbca33622069f7": {
        "$type": "RealismMod.WeaponMod, RealismMod",
        "ItemID": "203c45db79fbca33622069f7",
        "Name": "PGW Defense Timberwolf .338 Norma Mag 26 inch barrel",
        "ModType": "",
        "VerticalRecoil": -4,
        "HorizontalRecoil": 0,
        "AutoROF": 0,
        "SemiROF": 0,
        "ModMalfunctionChance": 0,
        "Convergence": 1,
        "Accuracy": 1,
        "CenterOfImpact": 0.03,
        "HeatFactor": 1.03,
        "CoolFactor": 0.98,
        "DurabilityBurnModificator": 1,
        "Velocity": 1,
        "ConflictingItems": [
            "5a6086ea4f39f99cd479502f",
            "5a608bf24f39f98ffc77720e",
            "58dd3ad986f77403051cba8f",
            "5e023e53d4353e3302577c4c",
            "5efb0c1bd79ff02a1f5e68d9",
            "5e023e6e34d52a55c3304f71",
            "5e023e88277cce2b522ff2b1"
        ],
        "Ergonomics": -20.5,
        "Weight": 1.93,
        "ShotgunDispersion": 1,
        "Loudness": 0,
        "LoyaltyLevel": 3
    },
    "07514b8fc5d75c3adb78c64c": {
        "$type": "RealismMod.WeaponMod, RealismMod",
        "ItemID": "07514b8fc5d75c3adb78c64c",
        "Name": "X-Caliber 416R Stainless Fluted .338 Norma Mag 28 inch barrel",
        "ModType": "",
        "VerticalRecoil": 0,
        "HorizontalRecoil": 0,
        "AutoROF": 0,
        "SemiROF": 0,
        "ModMalfunctionChance": 0,
        "Convergence": 6,
        "Accuracy": 1,
        "CenterOfImpact": 0.04,
        "HeatFactor": 1.01,
        "CoolFactor": 0.98,
        "DurabilityBurnModificator": 1,
        "Velocity": 1.66,
        "ConflictingItems": [
            "5a6086ea4f39f99cd479502f",
            "5a608bf24f39f98ffc77720e",
            "58dd3ad986f77403051cba8f",
            "5e023e53d4353e3302577c4c",
            "5efb0c1bd79ff02a1f5e68d9",
            "5e023e6e34d52a55c3304f71",
            "5e023e88277cce2b522ff2b1"
        ],
        "Ergonomics": -21.5,
        "Weight": 1.93,
        "ShotgunDispersion": 1,
        "Loudness": 0,
        "LoyaltyLevel": 3
    },
    "5ad7771228e921777b30536f": {
        "$type": "RealismMod.WeaponMod, RealismMod",
        "ItemID": "5ad7771228e921777b30536f",
        "Name": "X-Caliber 416R Stainless Fluted .338 Norma Mag 26 inch barrel",
        "ModType": "",
        "VerticalRecoil": -4,
        "HorizontalRecoil": 0,
        "AutoROF": 0,
        "SemiROF": 0,
        "ModMalfunctionChance": 0,
        "Convergence": 9,
        "Accuracy": -1,
        "CenterOfImpact": 0.03,
        "HeatFactor": 0.98,
        "CoolFactor": 0.96,
        "DurabilityBurnModificator": 1,
        "Velocity": 2,
        "ConflictingItems": [
            "5a6086ea4f39f99cd479502f",
            "5a608bf24f39f98ffc77720e",
            "58dd3ad986f77403051cba8f",
            "5e023e53d4353e3302577c4c",
            "5efb0c1bd79ff02a1f5e68d9",
            "5e023e6e34d52a55c3304f71",
            "5e023e88277cce2b522ff2b1"
        ],
        "Ergonomics": -20.5,
        "Weight": 1.78,
        "ShotgunDispersion": 1,
        "Loudness": 0,
        "LoyaltyLevel": 3
    },
    "51c4d8a19eeb65f225154688": {
        "$type": "RealismMod.WeaponMod, RealismMod",
        "ItemID": "51c4d8a19eeb65f225154688",
        "Name": "X-Caliber 416R Stainless Fluted .338 Norma Mag 24 inch barrel",
        "ModType": "",
        "VerticalRecoil": -3,
        "HorizontalRecoil": 0,
        "AutoROF": 0,
        "SemiROF": 0,
        "ModMalfunctionChance": 0,
        "Convergence": 8,
        "Accuracy": 0,
        "CenterOfImpact": 0.03,
        "HeatFactor": 1.02,
        "CoolFactor": 0.96,
        "DurabilityBurnModificator": 1,
        "Velocity": 1.01,
        "ConflictingItems": [
            "5a6086ea4f39f99cd479502f",
            "5a608bf24f39f98ffc77720e",
            "58dd3ad986f77403051cba8f",
            "5e023e53d4353e3302577c4c",
            "5efb0c1bd79ff02a1f5e68d9",
            "5e023e6e34d52a55c3304f71",
            "5e023e88277cce2b522ff2b1"
        ],
        "Ergonomics": -19.5,
        "Weight": 1.489,
        "ShotgunDispersion": 1,
        "Loudness": 0,
        "LoyaltyLevel": 3
    },
    "b5764983c9a6fb507af2aeb3": {
        "$type": "RealismMod.WeaponMod, RealismMod",
        "ItemID": "b5764983c9a6fb507af2aeb3",
        "Name": "X-Caliber 416R Stainless Fluted .338 Norma Mag 22 inch barrel",
        "ModType": "",
        "VerticalRecoil": -2,
        "HorizontalRecoil": 0,
        "AutoROF": 0,
        "SemiROF": 0,
        "ModMalfunctionChance": 0,
        "Convergence": 1,
        "Accuracy": 0,
        "CenterOfImpact": 0.02,
        "HeatFactor": 1.0,
        "CoolFactor": 0.97,
        "DurabilityBurnModificator": 1,
        "Velocity": -1.21,
        "ConflictingItems": [
            "5a6086ea4f39f99cd479502f",
            "5a608bf24f39f98ffc77720e",
            "58dd3ad986f77403051cba8f",
            "5e023e53d4353e3302577c4c",
            "5efb0c1bd79ff02a1f5e68d9",
            "5e023e6e34d52a55c3304f71",
            "5e023e88277cce2b522ff2b1"
        ],
        "Ergonomics": -18.5,
        "Weight": 1.343,
        "ShotgunDispersion": 1,
        "Loudness": 0,
        "LoyaltyLevel": 3
    },
    "0e60e51a2dce673d5ed173bf": {
        "$type": "RealismMod.WeaponMod, RealismMod",
        "ItemID": "0e60e51a2dce673d5ed173bf",
        "Name": "X-Caliber 416R Stainless Fluted .338 Norma Mag 20 inch barrel",
        "ModType": "",
        "VerticalRecoil": -1,
        "HorizontalRecoil": 0,
        "AutoROF": 0,
        "SemiROF": 0,
        "ModMalfunctionChance": 0,
        "Convergence": 5,
        "Accuracy": 1,
        "CenterOfImpact": 0.03,
        "HeatFactor": 1.0,
        "CoolFactor": 0.98,
        "DurabilityBurnModificator": 1,
        "Velocity": 2.86,
        "ConflictingItems": [
            "5a6086ea4f39f99cd479502f",
            "5a608bf24f39f98ffc77720e",
            "58dd3ad986f77403051cba8f",
            "5e023e53d4353e3302577c4c",
            "5efb0c1bd79ff02a1f5e68d9",
            "5e023e6e34d52a55c3304f71",
            "5e023e88277cce2b522ff2b1"
        ],
        "Ergonomics": -17.5,
        "Weight": 1.196,
        "ShotgunDispersion": 1,
        "Loudness": 0,
        "LoyaltyLevel": 3
    },
    "2094b55ae444de6c8a241d48": {
        "$type": "RealismMod.WeaponMod, RealismMod",
        "ItemID": "2094b55ae444de6c8a241d48",
        "Name": "X-Caliber 416R Stainless Fluted .338 Norma Mag 18 inch barrel",
        "ModType": "",
        "VerticalRecoil": 0,
        "HorizontalRecoil": 0,
        "AutoROF": 0,
        "SemiROF": 0,
        "ModMalfunctionChance": 0,
        "Convergence": 2,
        "Accuracy": 2,
        "CenterOfImpact": 0.03,
        "HeatFactor": 1.01,
        "CoolFactor": 0.96,
        "DurabilityBurnModificator": 1,
        "Velocity": 2.33,
        "ConflictingItems": [
            "5a6086ea4f39f99cd479502f",
            "5a608bf24f39f98ffc77720e",
            "58dd3ad986f77403051cba8f",
            "5e023e53d4353e3302577c4c",
            "5efb0c1bd79ff02a1f5e68d9",
            "5e023e6e34d52a55c3304f71",
            "5e023e88277cce2b522ff2b1"
        ],
        "Ergonomics": -16.5,
        "Weight": 1.049,
        "ShotgunDispersion": 1,
        "Loudness": 5,
        "LoyaltyLevel": 3
    },
    "924d08fd140d56bc7e395091": {
        "$type": "RealismMod.WeaponMod, RealismMod",
        "ItemID": "924d08fd140d56bc7e395091",
        "Name": "X-Caliber 416R Stainless Fluted .338 Norma Mag 16 inch barrel",
        "ModType": "",
        "VerticalRecoil": 1,
        "HorizontalRecoil": 0,
        "AutoROF": 0,
        "SemiROF": 0,
        "ModMalfunctionChance": 0,
        "Convergence": 1,
        "Accuracy": 1,
        "CenterOfImpact": 0.02,
        "HeatFactor": 1.03,
        "CoolFactor": 1.01,
        "DurabilityBurnModificator": 1,
        "Velocity": 0.64,
        "ConflictingItems": [
            "5a6086ea4f39f99cd479502f",
            "5a608bf24f39f98ffc77720e",
            "58dd3ad986f77403051cba8f",
            "5e023e53d4353e3302577c4c",
            "5efb0c1bd79ff02a1f5e68d9",
            "5e023e6e34d52a55c3304f71",
            "5e023e88277cce2b522ff2b1"
        ],
        "Ergonomics": -15.5,
        "Weight": 0.903,
        "ShotgunDispersion": 1,
        "Loudness": 10,
        "LoyaltyLevel": 3
    },
    "c68564cf5a0d02bc54ea5725": {
        "$type": "RealismMod.WeaponMod, RealismMod",
        "ItemID": "c68564cf5a0d02bc54ea5725",
        "Name": "X-Caliber 416R Stainless Fluted .338 Norma Mag 14 inch barrel",
        "ModType": "",
        "VerticalRecoil": 2,
        "HorizontalRecoil": 0,
        "AutoROF": 0,
        "SemiROF": 0,
        "ModMalfunctionChance": 0,
        "Convergence": 3,
        "Accuracy": 1,
        "CenterOfImpact": 0.03,
        "HeatFactor": 1.01,
        "CoolFactor": 0.98,
        "DurabilityBurnModificator": 1,
        "Velocity": 0.49,
        "ConflictingItems": [
            "5a6086ea4f39f99cd479502f",
            "5a608bf24f39f98ffc77720e",
            "58dd3ad986f77403051cba8f",
            "5e023e53d4353e3302577c4c",
            "5efb0c1bd79ff02a1f5e68d9",
            "5e023e6e34d52a55c3304f71",
            "5e023e88277cce2b522ff2b1"
        ],
        "Ergonomics": -14.5,
        "Weight": 0.756,
        "ShotgunDispersion": 1,
        "Loudness": 15,
        "LoyaltyLevel": 3
    },
    "c572ff3cb1b04b5dd73e615b": {
        "$type": "RealismMod.WeaponMod, RealismMod",
        "ItemID": "c572ff3cb1b04b5dd73e615b",
        "Name": "Badger Ordnance IMUNS for AICS 2.0 chassis",
        "ModType": "",
        "Ergonomics": 0,
        "Accuracy": 0,
        "ConflictingItems": [
            "5947db3f86f77447880cf76f",
            "57486e672459770abd687134",
            "576fd4ec2459777f0b518431",
            "5a7c74b3e899ef0014332c29",
            "591ee00d86f774592f7b841e",
            "57acb6222459771ec34b5cb0"
        ],
        "Weight": 0.28,
        "LoyaltyLevel": 3
    },
    "70493dc2459f53ff14b14175": {
        "$type": "RealismMod.WeaponMod, RealismMod",
        "ItemID": "70493dc2459f53ff14b14175",
        "Name": "Badger Ordnance IMUNS side rail",
        "ModType": "",
        "Ergonomics": 0,
        "Accuracy": 0,
        "ConflictingItems": [
            "5947db3f86f77447880cf76f",
            "57486e672459770abd687134",
            "576fd4ec2459777f0b518431",
            "5a7c74b3e899ef0014332c29",
            "591ee00d86f774592f7b841e",
            "57acb6222459771ec34b5cb0"
        ],
        "Weight": 0.28,
        "LoyaltyLevel": 3
    },
    "ec7a054379216e7ccf2d35f7": {
        "$type": "RealismMod.WeaponMod, RealismMod",
        "ItemID": "ec7a054379216e7ccf2d35f7",
        "Name": "MDT XTN to buffer tube adapter",
        "ModType": "",
        "VerticalRecoil": 3,
        "HorizontalRecoil": 3,
        "Dispersion": 0,
        "CameraRecoil": 0,
        "AimSpeed": 0,
        "Ergonomics": 1,
        "Accuracy": 0,
        "HasShoulderContact": false,
        "BlocksFolding": false,
        "AutoROF": 0,
        "SemiROF": 0,
        "ModMalfunctionChance": 0,
        "StockAllowADS": false,
        "ConflictingItems": [],
        "Weight": 0.12,
        "HeatFactor": 1,
        "CoolFactor": 1,
        "LoyaltyLevel": 2
    },
    "c8548cdf0e490383177f37c1": {
        "$type": "RealismMod.WeaponMod, RealismMod",
        "ItemID": "c8548cdf0e490383177f37c1",
        "Name": "PGW Defense C14 Timberwolf .338 LM sound suppressor",
        "ModType": "",
        "VerticalRecoil": -14,
        "HorizontalRecoil": -8,
        "Dispersion": -4,
        "CameraRecoil": -5,
        "AutoROF": 2,
        "SemiROF": 2.8,
        "ModMalfunctionChance": 12,
        "CanCycleSubs": true,
        "Accuracy": 2,
        "HeatFactor": 1.16,
        "CoolFactor": 1.1,
        "DurabilityBurnModificator": 1.3,
        "Velocity": 1.15,
        "RecoilAngle": 0,
        "ConflictingItems": [],
        "Ergonomics": -12,
        "Weight": 1.24,
        "ModShotDispersion": 0,
        "Loudness": -29,
        "Convergence": 0,
        "LoyaltyLevel": 4,
        "Flash": -37
    },
    "8c0343f717834fd6d4825a58": {
        "$type": "RealismMod.WeaponMod, RealismMod",
        "ItemID": "8c0343f717834fd6d4825a58",
        "Name": "PGW Defense C14 .338 LM muzzle brake",
        "ModType": "",
        "VerticalRecoil": -19,
        "HorizontalRecoil": -12,
        "Dispersion": -4,
        "CameraRecoil": -8,
        "AutoROF": 0,
        "SemiROF": 0,
        "ModMalfunctionChance": 0,
        "CanCycleSubs": false,
        "Accuracy": -1,
        "HeatFactor": 1,
        "CoolFactor": 1,
        "DurabilityBurnModificator": 1,
        "Velocity": 0,
        "RecoilAngle": 0,
        "ConflictingItems": [],
        "Ergonomics": -4,
        "Weight": 0.177,
        "Loudness": 17,
        "Convergence": 0,
        "LoyaltyLevel": 3,
        "Flash": 12
    },
    "ebd108b0a8c45420f7624a3f": {
        "$type": "RealismMod.WeaponMod, RealismMod",
        "ItemID": "ebd108b0a8c45420f7624a3f",
        "Name": "AR-15 MDT Elite pistol grip",
        "ModType": "",
        "VerticalRecoil": 0,
        "HorizontalRecoil": 0,
        "Dispersion": 0,
        "AimSpeed": 2,
        "Ergonomics": 2,
        "Accuracy": 3.5,
        "ConflictingItems": [],
        "Weight": 0.086,
        "LoyaltyLevel": 3,
        "AimStability": 3.21
    },
    "356e3ea40ac16f18c938ac53": {
        "$type": "RealismMod.WeaponMod, RealismMod",
        "ItemID": "356e3ea40ac16f18c938ac53",
        "Name": "McMillan A5 stock for Remington 700 long action (BLK)",
        "ModType": "StockR",
        "VerticalRecoil": -10,
        "HorizontalRecoil": -6,
        "Dispersion": -2,
        "CameraRecoil": -8,
        "AimSpeed": 1,
        "Ergonomics": 12,
        "Accuracy": 1.0,
        "HasShoulderContact": true,
        "BlocksFolding": false,
        "AutoROF": 0,
        "SemiROF": 0,
        "ModMalfunctionChance": 0,
        "StockAllowADS": false,
        "ConflictingItems": [
            "5d25a6538abbc306c62e630d",
            "5d25a4a98abbc30b917421a4",
            "5d25a7b88abbc3054f3e60bc",
            "5ce69cbad7f00c00b61c5098",
            "5d25a6a48abbc306c62e6310",
            "5d25af8f8abbc3055079fec5",
            "5cf12a15d7f00c05464b293f"
        ],
        "Weight": 2.587,
        "HeatFactor": 1,
        "CoolFactor": 1,
        "LoyaltyLevel": 1,
        "Handling": 2
    },
    "2fc4f74291323723f4e2b05d": {
        "$type": "RealismMod.WeaponMod, RealismMod",
        "ItemID": "2fc4f74291323723f4e2b05d",
        "Name": "McMillan A5 stock for Remington 700 long action (FDE)",
        "ModType": "StockR",
        "VerticalRecoil": -10,
        "HorizontalRecoil": -7,
        "Dispersion": -2,
        "CameraRecoil": -8,
        "AimSpeed": -4,
        "Ergonomics": 11,
        "Accuracy": 1.0,
        "HasShoulderContact": true,
        "BlocksFolding": false,
        "AutoROF": 0,
        "SemiROF": 0,
        "ModMalfunctionChance": 0,
        "StockAllowADS": false,
        "ConflictingItems": [
            "5d25a6538abbc306c62e630d",
            "5d25a4a98abbc30b917421a4",
            "5d25a7b88abbc3054f3e60bc",
            "5ce69cbad7f00c00b61c5098",
            "5d25a6a48abbc306c62e6310",
            "5d25af8f8abbc3055079fec5",
            "5cf12a15d7f00c05464b293f"
        ],
        "Weight": 2.587,
        "HeatFactor": 1,
        "CoolFactor": 1,
        "LoyaltyLevel": 1,
        "Handling": 4
    },
    "ef91b747041c9337fd9a711b": {
        "$type": "RealismMod.WeaponMod, RealismMod",
        "ItemID": "ef91b747041c9337fd9a711b",
        "Name": "McMillan A5 stock for Remington 700 long action (ODG)",
        "ModType": "StockR",
        "VerticalRecoil": -9,
        "HorizontalRecoil": -6,
        "Dispersion": -2,
        "CameraRecoil": -8,
        "AimSpeed": -2,
        "Ergonomics": 10,
        "Accuracy": 1.0,
        "HasShoulderContact": true,
        "BlocksFolding": false,
        "AutoROF": 0,
        "SemiROF": 0,
        "ModMalfunctionChance": 0,
        "StockAllowADS": false,
        "ConflictingItems": [
            "5d25a6538abbc306c62e630d",
            "5d25a4a98abbc30b917421a4",
            "5d25a7b88abbc3054f3e60bc",
            "5ce69cbad7f00c00b61c5098",
            "5d25a6a48abbc306c62e6310",
            "5d25af8f8abbc3055079fec5",
            "5cf12a15d7f00c05464b293f"
        ],
        "Weight": 2.587,
        "HeatFactor": 1,
        "CoolFactor": 1,
        "LoyaltyLevel": 1,
        "Handling": 2
    },
    "c0a00711f992a1aecdc53ae0": {
        "$type": "RealismMod.WeaponMod, RealismMod",
        "ItemID": "c0a00711f992a1aecdc53ae0",
        "Name": "Accuracy International AT AICS chassis for Remington 700 long action",
        "ModType": "StockN",
        "VerticalRecoil": -9,
        "HorizontalRecoil": -6,
        "Dispersion": -12,
        "CameraRecoil": -9,
        "AimSpeed": -3,
        "Ergonomics": 13,
        "Accuracy": 12.0,
        "HasShoulderContact": true,
        "BlocksFolding": false,
        "AutoROF": 0,
        "SemiROF": 0,
        "ModMalfunctionChance": 0,
        "StockAllowADS": false,
        "ConflictingItems": [
            "5d25af8f8abbc3055079fec5",
            "5cf12a15d7f00c05464b293f",
            "5bfeaa0f0db834001b734927",
            "5bfea7ad0db834001c38f1ee"
        ],
        "Weight": 3.471,
        "HeatFactor": 1,
        "CoolFactor": 1,
        "LoyaltyLevel": 3,
        "AimStability": 12,
        "Handling": 1
    },
    "275dd0d822b1fcaeb831ff87": {
        "$type": "RealismMod.WeaponMod, RealismMod",
        "ItemID": "275dd0d822b1fcaeb831ff87",
        "Name": "MDT ESS chassis for Remington 700 long action",
        "ModType": "StockN",
        "VerticalRecoil": -8,
        "HorizontalRecoil": -7,
        "Dispersion": 0,
        "CameraRecoil": -8,
        "AimSpeed": 2,
        "Ergonomics": 11,
        "Accuracy": 17.5,
        "HasShoulderContact": false,
        "BlocksFolding": false,
        "AutoROF": 0,
        "SemiROF": 0,
        "ModMalfunctionChance": 0,
        "StockAllowADS": false,
        "ConflictingItems": [
            "5d25af8f8abbc3055079fec5",
            "5cf12a15d7f00c05464b293f",
            "5bfeaa0f0db834001b734927",
            "5bfea7ad0db834001c38f1ee"
        ],
        "Weight": 2.6,
        "HeatFactor": 1,
        "CoolFactor": 1,
        "LoyaltyLevel": 4
    },
    "29ac2a6601d5e966724ccb69": {
        "$type": "RealismMod.WeaponMod, RealismMod",
        "ItemID": "29ac2a6601d5e966724ccb69",
        "Name": "MDT Carbine buffer tube",
        "ModType": "buffer",
        "VerticalRecoil": 3,
        "HorizontalRecoil": 2,
        "Dispersion": 0,
        "CameraRecoil": 0,
        "AimSpeed": 0,
        "Ergonomics": 3,
        "Accuracy": 0,
        "HasShoulderContact": false,
        "BlocksFolding": false,
        "AutoROF": 0,
        "SemiROF": 0,
        "ModMalfunctionChance": 0,
        "StockAllowADS": false,
        "ConflictingItems": [],
        "Weight": 0.086,
        "DurabilityBurnModificator": 1,
        "LoyaltyLevel": 2
    },
    "48c722b422ad38933164b39c": {
        "$type": "RealismMod.WeaponMod, RealismMod",
        "ItemID": "48c722b422ad38933164b39c",
        "Name": "MDT SRS-X stock",
        "ModType": "StockR",
        "VerticalRecoil": -10,
        "HorizontalRecoil": -6,
        "Dispersion": -15,
        "CameraRecoil": -9,
        "AimSpeed": 2,
        "Ergonomics": 14,
        "Accuracy": 8,
        "HasShoulderContact": true,
        "BlocksFolding": false,
        "AutoROF": 0,
        "SemiROF": 0,
        "ModMalfunctionChance": 0,
        "StockAllowADS": false,
        "ConflictingItems": [],
        "Weight": 0.76,
        "LoyaltyLevel": 3,
        "AimStability": 10
    }
}