{
    "67fd89d05567aff486d5083a": {
        "$type": "RealismMod.WeaponMod, RealismMod",
        "ModType": "",
        "Ergonomics": 0,
        "Weight": 0.1,
        "ConflictingItems": [],
        "LoyaltyLevel": 1,
        "VerticalRecoil": 0,
        "HorizontalRecoil": 0,
        "AimSpeed": 0,
        "Accuracy": 0,
        "ItemID": "67fd89d05567aff486d5083a",
        "Name": "mod_67fd89d05567aff486d5083a"
    },
    "67fd8ed16987d666dc9ac61c": {
        "$type": "RealismMod.WeaponMod, RealismMod",
        "ModType": "",
        "Ergonomics": 0,
        "Weight": 0.1,
        "ConflictingItems": [],
        "LoyaltyLevel": 1,
        "VerticalRecoil": 0,
        "HorizontalRecoil": 0,
        "AimSpeed": 0,
        "Accuracy": 0,
        "ItemID": "67fd8ed16987d666dc9ac61c",
        "Name": "mod_67fd8ed16987d666dc9ac61c"
    },
    "67fd8ece241d10336042d4b9": {
        "$type": "RealismMod.WeaponMod, RealismMod",
        "ModType": "",
        "Ergonomics": 0,
        "Weight": 0.1,
        "ConflictingItems": [],
        "LoyaltyLevel": 1,
        "VerticalRecoil": 0,
        "HorizontalRecoil": 0,
        "AimSpeed": 0,
        "Accuracy": 0,
        "ItemID": "67fd8ece241d10336042d4b9",
        "Name": "mod_67fd8ece241d10336042d4b9"
    },
    "67fd8ecc9183ad20bb523e7d": {
        "$type": "RealismMod.WeaponMod, RealismMod",
        "ModType": "",
        "Ergonomics": 0,
        "Weight": 0.1,
        "ConflictingItems": [],
        "LoyaltyLevel": 1,
        "VerticalRecoil": 0,
        "HorizontalRecoil": 0,
        "AimSpeed": 0,
        "Accuracy": 0,
        "ItemID": "67fd8ecc9183ad20bb523e7d",
        "Name": "mod_67fd8ecc9183ad20bb523e7d"
    },
    "67fd8ec861773f3ce6e7de2e": {
        "$type": "RealismMod.WeaponMod, RealismMod",
        "ModType": "",
        "Ergonomics": 0,
        "Weight": 0.1,
        "ConflictingItems": [],
        "LoyaltyLevel": 1,
        "VerticalRecoil": 0,
        "HorizontalRecoil": 0,
        "AimSpeed": 0,
        "Accuracy": 0,
        "ItemID": "67fd8ec861773f3ce6e7de2e",
        "Name": "mod_67fd8ec861773f3ce6e7de2e"
    },
    "67fd8ec664e36ab00141b370": {
        "$type": "RealismMod.WeaponMod, RealismMod",
        "ModType": "",
        "Ergonomics": 0,
        "Weight": 0.1,
        "ConflictingItems": [],
        "LoyaltyLevel": 1,
        "VerticalRecoil": 0,
        "HorizontalRecoil": 0,
        "AimSpeed": 0,
        "Accuracy": 0,
        "ItemID": "67fd8ec664e36ab00141b370",
        "Name": "mod_67fd8ec664e36ab00141b370"
    },
    "67fd8ec1e542b3e3b8c44711": {
        "$type": "RealismMod.WeaponMod, RealismMod",
        "ModType": "",
        "Ergonomics": 0,
        "Weight": 0.1,
        "ConflictingItems": [],
        "LoyaltyLevel": 1,
        "VerticalRecoil": 0,
        "HorizontalRecoil": 0,
        "AimSpeed": 0,
        "Accuracy": 0,
        "ItemID": "67fd8ec1e542b3e3b8c44711",
        "Name": "mod_67fd8ec1e542b3e3b8c44711"
    },
    "67fd9042de33966ae01f6d0c": {
        "$type": "RealismMod.WeaponMod, RealismMod",
        "ModType": "",
        "Ergonomics": 0,
        "Weight": 0.1,
        "ConflictingItems": [],
        "LoyaltyLevel": 1,
        "VerticalRecoil": 0,
        "HorizontalRecoil": 0,
        "AimSpeed": 0,
        "Accuracy": 0,
        "ItemID": "67fd9042de33966ae01f6d0c",
        "Name": "mod_67fd9042de33966ae01f6d0c"
    },
    "67fd9034b98d305f9ad4b734": {
        "$type": "RealismMod.WeaponMod, RealismMod",
        "ModType": "",
        "Ergonomics": 0,
        "Weight": 0.1,
        "ConflictingItems": [],
        "LoyaltyLevel": 1,
        "VerticalRecoil": 0,
        "HorizontalRecoil": 0,
        "AimSpeed": 0,
        "Accuracy": 0,
        "ItemID": "67fd9034b98d305f9ad4b734",
        "Name": "mod_67fd9034b98d305f9ad4b734"
    },
    "67fd90269d7183baa12a345c": {
        "$type": "RealismMod.WeaponMod, RealismMod",
        "ModType": "",
        "Ergonomics": 0,
        "Weight": 0.1,
        "ConflictingItems": [],
        "LoyaltyLevel": 1,
        "VerticalRecoil": 0,
        "HorizontalRecoil": 0,
        "AimSpeed": 0,
        "Accuracy": 0,
        "ItemID": "67fd90269d7183baa12a345c",
        "Name": "mod_67fd90269d7183baa12a345c"
    },
    "67fd90173083497931438010": {
        "$type": "RealismMod.WeaponMod, RealismMod",
        "ModType": "",
        "Ergonomics": 0,
        "Weight": 0.1,
        "ConflictingItems": [],
        "LoyaltyLevel": 1,
        "VerticalRecoil": 0,
        "HorizontalRecoil": 0,
        "AimSpeed": 0,
        "Accuracy": 0,
        "ItemID": "67fd90173083497931438010",
        "Name": "mod_67fd90173083497931438010"
    },
    "67fd900484a5ab104d95e97f": {
        "$type": "RealismMod.WeaponMod, RealismMod",
        "ModType": "",
        "Ergonomics": 0,
        "Weight": 0.1,
        "ConflictingItems": [],
        "LoyaltyLevel": 1,
        "VerticalRecoil": 0,
        "HorizontalRecoil": 0,
        "AimSpeed": 0,
        "Accuracy": 0,
        "ItemID": "67fd900484a5ab104d95e97f",
        "Name": "mod_67fd900484a5ab104d95e97f"
    },
    "67fd8fe3cd88b807386fc5ce": {
        "$type": "RealismMod.WeaponMod, RealismMod",
        "ModType": "",
        "Ergonomics": 0,
        "Weight": 0.1,
        "ConflictingItems": [],
        "LoyaltyLevel": 1,
        "VerticalRecoil": 0,
        "HorizontalRecoil": 0,
        "AimSpeed": 0,
        "Accuracy": 0,
        "ItemID": "67fd8fe3cd88b807386fc5ce",
        "Name": "mod_67fd8fe3cd88b807386fc5ce"
    },
    "67fd8fd1e83506175a44dd5e": {
        "$type": "RealismMod.WeaponMod, RealismMod",
        "ModType": "",
        "Ergonomics": 0,
        "Weight": 0.1,
        "ConflictingItems": [],
        "LoyaltyLevel": 1,
        "VerticalRecoil": 0,
        "HorizontalRecoil": 0,
        "AimSpeed": 0,
        "Accuracy": 0,
        "ItemID": "67fd8fd1e83506175a44dd5e",
        "Name": "mod_67fd8fd1e83506175a44dd5e"
    },
    "67fd963c66b904fc4fe55316": {
        "$type": "RealismMod.WeaponMod, RealismMod",
        "ModType": "",
        "Ergonomics": 0,
        "Weight": 0.1,
        "ConflictingItems": [],
        "LoyaltyLevel": 1,
        "VerticalRecoil": 0,
        "HorizontalRecoil": 0,
        "AimSpeed": 0,
        "Accuracy": 0,
        "ItemID": "67fd963c66b904fc4fe55316",
        "Name": "mod_67fd963c66b904fc4fe55316"
    },
    "67fd97cacbba67881c88d6fc": {
        "$type": "RealismMod.WeaponMod, RealismMod",
        "ModType": "",
        "Ergonomics": 0,
        "Weight": 0.1,
        "ConflictingItems": [],
        "LoyaltyLevel": 1,
        "VerticalRecoil": 0,
        "HorizontalRecoil": 0,
        "AimSpeed": 0,
        "Accuracy": 0,
        "ItemID": "67fd97cacbba67881c88d6fc",
        "Name": "mod_67fd97cacbba67881c88d6fc"
    },
    "67fd9a9bdbc4d142684fcf76": {
        "$type": "RealismMod.WeaponMod, RealismMod",
        "ModType": "",
        "Ergonomics": 0,
        "Weight": 0.1,
        "ConflictingItems": [],
        "LoyaltyLevel": 1,
        "VerticalRecoil": 0,
        "HorizontalRecoil": 0,
        "AimSpeed": 0,
        "Accuracy": 0,
        "ItemID": "67fd9a9bdbc4d142684fcf76",
        "Name": "mod_67fd9a9bdbc4d142684fcf76"
    },
    "67fd9a957c70da76f87fa5c5": {
        "$type": "RealismMod.WeaponMod, RealismMod",
        "ModType": "",
        "Ergonomics": 0,
        "Weight": 0.1,
        "ConflictingItems": [],
        "LoyaltyLevel": 1,
        "VerticalRecoil": 0,
        "HorizontalRecoil": 0,
        "AimSpeed": 0,
        "Accuracy": 0,
        "ItemID": "67fd9a957c70da76f87fa5c5",
        "Name": "mod_67fd9a957c70da76f87fa5c5"
    },
    "67fd9a8944d90d78dedc8e3a": {
        "$type": "RealismMod.WeaponMod, RealismMod",
        "ModType": "",
        "Ergonomics": 0,
        "Weight": 0.1,
        "ConflictingItems": [],
        "LoyaltyLevel": 1,
        "VerticalRecoil": 0,
        "HorizontalRecoil": 0,
        "AimSpeed": 0,
        "Accuracy": 0,
        "ItemID": "67fd9a8944d90d78dedc8e3a",
        "Name": "mod_67fd9a8944d90d78dedc8e3a"
    },
    "67fd9a7038c98b76b3278d0b": {
        "$type": "RealismMod.WeaponMod, RealismMod",
        "ModType": "",
        "Ergonomics": 0,
        "Weight": 0.1,
        "ConflictingItems": [],
        "LoyaltyLevel": 1,
        "VerticalRecoil": 0,
        "HorizontalRecoil": 0,
        "AimSpeed": 0,
        "Accuracy": 0,
        "ItemID": "67fd9a7038c98b76b3278d0b",
        "Name": "mod_67fd9a7038c98b76b3278d0b"
    },
    "67fd9a690dbb3540dfb1cb45": {
        "$type": "RealismMod.WeaponMod, RealismMod",
        "ModType": "",
        "Ergonomics": 0,
        "Weight": 0.1,
        "ConflictingItems": [],
        "LoyaltyLevel": 1,
        "VerticalRecoil": 0,
        "HorizontalRecoil": 0,
        "AimSpeed": 0,
        "Accuracy": 0,
        "ItemID": "67fd9a690dbb3540dfb1cb45",
        "Name": "mod_67fd9a690dbb3540dfb1cb45"
    },
    "67fd9a66e374fdee6ac887f4": {
        "$type": "RealismMod.WeaponMod, RealismMod",
        "ModType": "",
        "Ergonomics": 0,
        "Weight": 0.1,
        "ConflictingItems": [],
        "LoyaltyLevel": 1,
        "VerticalRecoil": 0,
        "HorizontalRecoil": 0,
        "AimSpeed": 0,
        "Accuracy": 0,
        "ItemID": "67fd9a66e374fdee6ac887f4",
        "Name": "mod_67fd9a66e374fdee6ac887f4"
    },
    "67fd9dda8f0e8418c7929856": {
        "$type": "RealismMod.WeaponMod, RealismMod",
        "ModType": "",
        "Ergonomics": 0,
        "Weight": 0.1,
        "ConflictingItems": [],
        "LoyaltyLevel": 1,
        "VerticalRecoil": 0,
        "HorizontalRecoil": 0,
        "AimSpeed": 0,
        "Accuracy": 0,
        "ItemID": "67fd9dda8f0e8418c7929856",
        "Name": "mod_67fd9dda8f0e8418c7929856"
    },
    "67fd9ea9d662d6d315f006c3": {
        "$type": "RealismMod.WeaponMod, RealismMod",
        "ModType": "",
        "Ergonomics": 0,
        "Weight": 0.1,
        "ConflictingItems": [],
        "LoyaltyLevel": 1,
        "VerticalRecoil": 0,
        "HorizontalRecoil": 0,
        "AimSpeed": 0,
        "Accuracy": 0,
        "ItemID": "67fd9ea9d662d6d315f006c3",
        "Name": "mod_67fd9ea9d662d6d315f006c3"
    },
    "67fd9ea2d52b96af77cd20e2": {
        "$type": "RealismMod.WeaponMod, RealismMod",
        "ModType": "",
        "Ergonomics": 0,
        "Weight": 0.1,
        "ConflictingItems": [],
        "LoyaltyLevel": 1,
        "VerticalRecoil": 0,
        "HorizontalRecoil": 0,
        "AimSpeed": 0,
        "Accuracy": 0,
        "ItemID": "67fd9ea2d52b96af77cd20e2",
        "Name": "mod_67fd9ea2d52b96af77cd20e2"
    },
    "67fd9e96fd83cd8eebbba504": {
        "$type": "RealismMod.WeaponMod, RealismMod",
        "ModType": "",
        "Ergonomics": 0,
        "Weight": 0.1,
        "ConflictingItems": [],
        "LoyaltyLevel": 1,
        "VerticalRecoil": 0,
        "HorizontalRecoil": 0,
        "AimSpeed": 0,
        "Accuracy": 0,
        "ItemID": "67fd9e96fd83cd8eebbba504",
        "Name": "mod_67fd9e96fd83cd8eebbba504"
    },
    "67fd9e92609d6554686019be": {
        "$type": "RealismMod.WeaponMod, RealismMod",
        "ModType": "",
        "Ergonomics": 0,
        "Weight": 0.1,
        "ConflictingItems": [],
        "LoyaltyLevel": 1,
        "VerticalRecoil": 0,
        "HorizontalRecoil": 0,
        "AimSpeed": 0,
        "Accuracy": 0,
        "ItemID": "67fd9e92609d6554686019be",
        "Name": "mod_67fd9e92609d6554686019be"
    },
    "67fd9e8becc5dccab608f73f": {
        "$type": "RealismMod.WeaponMod, RealismMod",
        "ModType": "",
        "Ergonomics": 0,
        "Weight": 0.1,
        "ConflictingItems": [],
        "LoyaltyLevel": 1,
        "VerticalRecoil": 0,
        "HorizontalRecoil": 0,
        "AimSpeed": 0,
        "Accuracy": 0,
        "ItemID": "67fd9e8becc5dccab608f73f",
        "Name": "mod_67fd9e8becc5dccab608f73f"
    },
    "67fda2f6b346f4286b4d0eb2": {
        "$type": "RealismMod.WeaponMod, RealismMod",
        "ModType": "",
        "Ergonomics": 0,
        "Weight": 0.1,
        "ConflictingItems": [],
        "LoyaltyLevel": 1,
        "VerticalRecoil": 0,
        "HorizontalRecoil": 0,
        "AimSpeed": 0,
        "Accuracy": 0,
        "ItemID": "67fda2f6b346f4286b4d0eb2",
        "Name": "mod_67fda2f6b346f4286b4d0eb2"
    },
    "67fda3ab5ff9996ae6760d69": {
        "$type": "RealismMod.WeaponMod, RealismMod",
        "ModType": "",
        "Ergonomics": 0,
        "Weight": 0.1,
        "ConflictingItems": [],
        "LoyaltyLevel": 1,
        "VerticalRecoil": 0,
        "HorizontalRecoil": 0,
        "AimSpeed": 0,
        "Accuracy": 0,
        "ItemID": "67fda3ab5ff9996ae6760d69",
        "Name": "mod_67fda3ab5ff9996ae6760d69"
    },
    "67fda3a1ddef42997a5b3439": {
        "$type": "RealismMod.WeaponMod, RealismMod",
        "ModType": "",
        "Ergonomics": 0,
        "Weight": 0.1,
        "ConflictingItems": [],
        "LoyaltyLevel": 1,
        "VerticalRecoil": 0,
        "HorizontalRecoil": 0,
        "AimSpeed": 0,
        "Accuracy": 0,
        "ItemID": "67fda3a1ddef42997a5b3439",
        "Name": "mod_67fda3a1ddef42997a5b3439"
    },
    "67fda3999cf6a700c0758ed3": {
        "$type": "RealismMod.WeaponMod, RealismMod",
        "ModType": "",
        "Ergonomics": 0,
        "Weight": 0.1,
        "ConflictingItems": [],
        "LoyaltyLevel": 1,
        "VerticalRecoil": 0,
        "HorizontalRecoil": 0,
        "AimSpeed": 0,
        "Accuracy": 0,
        "ItemID": "67fda3999cf6a700c0758ed3",
        "Name": "mod_67fda3999cf6a700c0758ed3"
    },
    "67fda38eab9c576d133a4ee2": {
        "$type": "RealismMod.WeaponMod, RealismMod",
        "ModType": "",
        "Ergonomics": 0,
        "Weight": 0.1,
        "ConflictingItems": [],
        "LoyaltyLevel": 1,
        "VerticalRecoil": 0,
        "HorizontalRecoil": 0,
        "AimSpeed": 0,
        "Accuracy": 0,
        "ItemID": "67fda38eab9c576d133a4ee2",
        "Name": "mod_67fda38eab9c576d133a4ee2"
    },
    "67fda384bf34a78433e37a41": {
        "$type": "RealismMod.WeaponMod, RealismMod",
        "ModType": "",
        "Ergonomics": 0,
        "Weight": 0.1,
        "ConflictingItems": [],
        "LoyaltyLevel": 1,
        "VerticalRecoil": 0,
        "HorizontalRecoil": 0,
        "AimSpeed": 0,
        "Accuracy": 0,
        "ItemID": "67fda384bf34a78433e37a41",
        "Name": "mod_67fda384bf34a78433e37a41"
    },
    "67fda377bf9ad922e419dfd9": {
        "$type": "RealismMod.WeaponMod, RealismMod",
        "ModType": "",
        "Ergonomics": 0,
        "Weight": 0.1,
        "ConflictingItems": [],
        "LoyaltyLevel": 1,
        "VerticalRecoil": 0,
        "HorizontalRecoil": 0,
        "AimSpeed": 0,
        "Accuracy": 0,
        "ItemID": "67fda377bf9ad922e419dfd9",
        "Name": "mod_67fda377bf9ad922e419dfd9"
    },
    "67fda36ac4d1a293897d0364": {
        "$type": "RealismMod.WeaponMod, RealismMod",
        "ModType": "",
        "Ergonomics": 0,
        "Weight": 0.1,
        "ConflictingItems": [],
        "LoyaltyLevel": 1,
        "VerticalRecoil": 0,
        "HorizontalRecoil": 0,
        "AimSpeed": 0,
        "Accuracy": 0,
        "ItemID": "67fda36ac4d1a293897d0364",
        "Name": "mod_67fda36ac4d1a293897d0364"
    },
    "67fda4bcb09758839cd67b18": {
        "$type": "RealismMod.WeaponMod, RealismMod",
        "ModType": "",
        "Ergonomics": 0,
        "Weight": 0.1,
        "ConflictingItems": [],
        "LoyaltyLevel": 1,
        "VerticalRecoil": 0,
        "HorizontalRecoil": 0,
        "AimSpeed": 0,
        "Accuracy": 0,
        "ItemID": "67fda4bcb09758839cd67b18",
        "Name": "mod_67fda4bcb09758839cd67b18"
    },
    "67fda520f0d87efb3405e7a1": {
        "$type": "RealismMod.WeaponMod, RealismMod",
        "ModType": "",
        "Ergonomics": 0,
        "Weight": 0.1,
        "ConflictingItems": [],
        "LoyaltyLevel": 1,
        "VerticalRecoil": 0,
        "HorizontalRecoil": 0,
        "AimSpeed": 0,
        "Accuracy": 0,
        "ItemID": "67fda520f0d87efb3405e7a1",
        "Name": "mod_67fda520f0d87efb3405e7a1"
    },
    "67fda5154db21c9111244af7": {
        "$type": "RealismMod.WeaponMod, RealismMod",
        "ModType": "",
        "Ergonomics": 0,
        "Weight": 0.1,
        "ConflictingItems": [],
        "LoyaltyLevel": 1,
        "VerticalRecoil": 0,
        "HorizontalRecoil": 0,
        "AimSpeed": 0,
        "Accuracy": 0,
        "ItemID": "67fda5154db21c9111244af7",
        "Name": "mod_67fda5154db21c9111244af7"
    },
    "67fda506e6cebe0df4bd6f28": {
        "$type": "RealismMod.WeaponMod, RealismMod",
        "ModType": "",
        "Ergonomics": 0,
        "Weight": 0.1,
        "ConflictingItems": [],
        "LoyaltyLevel": 1,
        "VerticalRecoil": 0,
        "HorizontalRecoil": 0,
        "AimSpeed": 0,
        "Accuracy": 0,
        "ItemID": "67fda506e6cebe0df4bd6f28",
        "Name": "mod_67fda506e6cebe0df4bd6f28"
    },
    "67fda4f8155446ae0831bb00": {
        "$type": "RealismMod.WeaponMod, RealismMod",
        "ModType": "",
        "Ergonomics": 0,
        "Weight": 0.1,
        "ConflictingItems": [],
        "LoyaltyLevel": 1,
        "VerticalRecoil": 0,
        "HorizontalRecoil": 0,
        "AimSpeed": 0,
        "Accuracy": 0,
        "ItemID": "67fda4f8155446ae0831bb00",
        "Name": "mod_67fda4f8155446ae0831bb00"
    },
    "67fda4eeb021a5bd5c76c351": {
        "$type": "RealismMod.WeaponMod, RealismMod",
        "ModType": "",
        "Ergonomics": 0,
        "Weight": 0.1,
        "ConflictingItems": [],
        "LoyaltyLevel": 1,
        "VerticalRecoil": 0,
        "HorizontalRecoil": 0,
        "AimSpeed": 0,
        "Accuracy": 0,
        "ItemID": "67fda4eeb021a5bd5c76c351",
        "Name": "mod_67fda4eeb021a5bd5c76c351"
    },
    "67fda4e6f82febbe285b3196": {
        "$type": "RealismMod.WeaponMod, RealismMod",
        "ModType": "",
        "Ergonomics": 0,
        "Weight": 0.1,
        "ConflictingItems": [],
        "LoyaltyLevel": 1,
        "VerticalRecoil": 0,
        "HorizontalRecoil": 0,
        "AimSpeed": 0,
        "Accuracy": 0,
        "ItemID": "67fda4e6f82febbe285b3196",
        "Name": "mod_67fda4e6f82febbe285b3196"
    },
    "67fda4db8cbb8bbc8a9ba0bf": {
        "$type": "RealismMod.WeaponMod, RealismMod",
        "ModType": "",
        "Ergonomics": 0,
        "Weight": 0.1,
        "ConflictingItems": [],
        "LoyaltyLevel": 1,
        "VerticalRecoil": 0,
        "HorizontalRecoil": 0,
        "AimSpeed": 0,
        "Accuracy": 0,
        "ItemID": "67fda4db8cbb8bbc8a9ba0bf",
        "Name": "mod_67fda4db8cbb8bbc8a9ba0bf"
    }
}