{
    "6628f2e31084cf4d62b2b40b": {
        "$type": "RealismMod.Gun, RealismMod",
        "ItemID": "6628f2e31084cf4d62b2b40b",
        "Name": "改装型 AUG A3 7.62x39 突击步枪",
        "WeapType": "",
        "OperationType": "",
        "WeapAccuracy": 0,
        "BaseTorque": 6,
        "HasShoulderContact": true,
        "Ergonomics": 83,
        "VerticalRecoil": 130,
        "HorizontalRecoil": 210,
        "Dispersion": 3.0,
        "CameraRecoil": 0.06,
        "VisualMulti": 1.25,
        "Convergence": 9.6,
        "RecoilAngle": 80,
        "BaseMalfunctionChance": 0.003,
        "HeatFactorGun": 0.4,
        "HeatFactorByShot": 1,
        "CoolFactorGun": 0.1,
        "CoolFactorGunMods": 1,
        "AllowOverheat": true,
        "CenterOfImpact": 0,
        "HipAccuracyRestorationDelay": 0.2,
        "HipAccuracyRestorationSpeed": 7,
        "HipInnaccuracyGain": 0.16,
        "ShotgunDispersion": 0,
        "Velocity": 0,
        "RecoilDamping": 0.87,
        "RecoilHandDamping": 0.5,
        "WeaponAllowADS": false,
        "Weight": 1.95,
        "DurabilityBurnRatio": 0.55,
        "AutoROF": 700,
        "SemiROF": 345,
        "LoyaltyLevel": 3,
        "BaseReloadSpeedMulti": 0.85,
        "BaseChamberSpeedMulti": 1,
        "MinChamberSpeed": 0.7,
        "MaxChamberSpeed": 1.5,
        "IsManuallyOperated": false,
        "BaseChamberCheckSpeed": 1,
        "BaseFixSpeed": 0.9,
        "OffsetRotation": 0.01,
        "RecoilIntensity": 0.23,
        "ConflictingItems": [
            "59e6920f86f77411d82aa167",
            "59e6927d86f77411da468256",
            "54527a984bdc2d4e668b4567",
            "54527ac44bdc2d36668b4567",
            "59e68f6f86f7746c9f75e846",
            "59e6906286f7746c9f75e847",
            "59e690b686f7746c9f75e848",
            "59e6918f86f7746c9f75e849",
            "60194943740c5d77f6705eea",
            "601949593ae8f707c4608daa",
            "5c0d5ae286f7741e46554302",
            "5fbe3ffdf8b6a877a729ea82",
            "5fd20ff893a8961fc660a954",
            "619636be6db0f2477964e710",
            "6196364158ef8c428c287d9f",
            "6196365d58ef8c428c287da1",
            "64b8725c4b75259c590fa899"
        ]
    },
    "6628f31d2e4dbf64427b378d": {
        "$type": "RealismMod.WeaponMod, RealismMod",
        "ItemID": "6628f31d2e4dbf64427b378d",
        "Name": "斯太尔 AUG 7.62x39 毫米 30 发弹匣",
        "ModType": "",
        "ReloadSpeed": 0,
        "Ergonomics": -1,
        "MalfunctionChance": 0,
        "LoadUnloadModifier": 5,
        "CheckTimeModifier": 1,
        "ConflictingItems": [],
        "Weight": 0.18,
        "VerticalRecoil": 0,
        "HorizontalRecoil": 0,
        "LoyaltyLevel": 3
    },
    "6628f33d585102d8bc5d75db": {
        "$type": "RealismMod.WeaponMod, RealismMod",
        "ItemID": "6628f33d585102d8bc5d75db",
        "Name": "斯太尔 AUG 7.62x39 毫米 42 发弹匣",
        "ModType": "",
        "ReloadSpeed": 0,
        "Ergonomics": -1,
        "MalfunctionChance": 0,
        "LoadUnloadModifier": 5,
        "CheckTimeModifier": 1,
        "ConflictingItems": [],
        "Weight": 0.18,
        "VerticalRecoil": 0,
        "HorizontalRecoil": 0,
        "LoyaltyLevel": 3
    }
}